opensearchpy/__init__.py
opensearchpy/__init__.pyi
opensearchpy/_version.py
opensearchpy/compat.py
opensearchpy/compat.pyi
opensearchpy/connection_pool.py
opensearchpy/connection_pool.pyi
opensearchpy/exceptions.py
opensearchpy/exceptions.pyi
opensearchpy/py.typed
opensearchpy/serializer.py
opensearchpy/serializer.pyi
opensearchpy/transport.py
opensearchpy/transport.pyi
opensearchpy/_async/__init__.py
opensearchpy/_async/_extra_imports.py
opensearchpy/_async/compat.py
opensearchpy/_async/compat.pyi
opensearchpy/_async/http_aiohttp.py
opensearchpy/_async/http_aiohttp.pyi
opensearchpy/_async/transport.py
opensearchpy/_async/transport.pyi
opensearchpy/_async/client/__init__.py
opensearchpy/_async/client/__init__.pyi
opensearchpy/_async/client/cat.py
opensearchpy/_async/client/cat.pyi
opensearchpy/_async/client/cluster.py
opensearchpy/_async/client/cluster.pyi
opensearchpy/_async/client/dangling_indices.py
opensearchpy/_async/client/dangling_indices.pyi
opensearchpy/_async/client/features.py
opensearchpy/_async/client/features.pyi
opensearchpy/_async/client/indices.py
opensearchpy/_async/client/indices.pyi
opensearchpy/_async/client/ingest.py
opensearchpy/_async/client/ingest.pyi
opensearchpy/_async/client/nodes.py
opensearchpy/_async/client/nodes.pyi
opensearchpy/_async/client/plugins.py
opensearchpy/_async/client/plugins.pyi
opensearchpy/_async/client/remote.py
opensearchpy/_async/client/remote.pyi
opensearchpy/_async/client/snapshot.py
opensearchpy/_async/client/snapshot.pyi
opensearchpy/_async/client/tasks.py
opensearchpy/_async/client/tasks.pyi
opensearchpy/_async/client/utils.py
opensearchpy/_async/client/utils.pyi
opensearchpy/_async/helpers/__init__.py
opensearchpy/_async/helpers/actions.py
opensearchpy/_async/helpers/actions.pyi
opensearchpy/_async/helpers/document.py
opensearchpy/_async/helpers/document.pyi
opensearchpy/_async/helpers/faceted_search.py
opensearchpy/_async/helpers/faceted_search.pyi
opensearchpy/_async/helpers/index.py
retakesearch_py-2.2.5.dist-info/AUTHORS
retakesearch_py-2.2.5.dist-info/LICENSE.txt
retakesearch_py-2.2.5.dist-info/METADATA
retakesearch_py-2.2.5.dist-info/NOTICE.txt
retakesearch_py-2.2.5.dist-info/WHEEL
retakesearch_py-2.2.5.dist-info/top_level.txt
retakesearch_py-2.2.5.dist-info/RECORD
