Metadata-Version: 2.1
Name: retakesearch-py
Version: 2.2.5
Summary: Python client for OpenSearch
Home-page: https://github.com/opensearch-project/opensearch-py
Author: Aleksei Atavin, Denis Zalevskiy, Rushi Agrawal, Shephali Mittal
Author-email: axeo@aiven.io, dez@aiven.io, rushi.agr@gmail.com, shephalm@amazon.com
Maintainer: Aleksei Atavin, Denis Zalevskiy, Rushi Agrawal, Shephali Mittal
Maintainer-email: axeo@aiven.io, dez@aiven.io, rushi.agr@gmail.com, shephalm@amazon.com
License: Apache-2.0
Project-URL: Documentation, https://opensearch.org/docs/clients/python
Project-URL: Source Code, https://github.com/opensearch-project/opensearch-py
Project-URL: Issue Tracker, https://github.com/opensearch-project/opensearch-py/issues
Classifier: Development Status :: 5 - Production/Stable
Classifier: License :: OSI Approved :: Apache Software License
Classifier: Intended Audience :: Developers
Classifier: Operating System :: OS Independent
Classifier: Programming Language :: Python
Classifier: Programming Language :: Python :: 2
Classifier: Programming Language :: Python :: 2.7
Classifier: Programming Language :: Python :: 3
Classifier: Programming Language :: Python :: 3.4
Classifier: Programming Language :: Python :: 3.5
Classifier: Programming Language :: Python :: 3.6
Classifier: Programming Language :: Python :: 3.7
Classifier: Programming Language :: Python :: 3.8
Classifier: Programming Language :: Python :: 3.9
Classifier: Programming Language :: Python :: Implementation :: CPython
Classifier: Programming Language :: Python :: Implementation :: PyPy
Requires-Python: >=2.7, !=3.0.*, !=3.1.*, !=3.2.*, !=3.3.*, <4
License-File: LICENSE.txt
License-File: NOTICE.txt
License-File: AUTHORS
Requires-Dist: urllib3 (<2,>=1.21.1)
Requires-Dist: requests (<3.0.0,>=2.4.0)
Requires-Dist: six
Requires-Dist: python-dateutil
Requires-Dist: certifi (>=2022.12.07)
Requires-Dist: ipaddress ; python_version < "3.3"
Provides-Extra: async
Requires-Dist: aiohttp (<4,>=3) ; extra == 'async'
Provides-Extra: develop
Requires-Dist: requests (<3.0.0,>=2.0.0) ; extra == 'develop'
Requires-Dist: coverage (<7.0.0) ; extra == 'develop'
Requires-Dist: mock ; extra == 'develop'
Requires-Dist: pyyaml ; extra == 'develop'
Requires-Dist: pytest (>=3.0.0) ; extra == 'develop'
Requires-Dist: pytest-cov ; extra == 'develop'
Requires-Dist: pytz ; extra == 'develop'
Requires-Dist: pytest-mock (<4.0.0) ; extra == 'develop'
Requires-Dist: sphinx ; extra == 'develop'
Requires-Dist: sphinx-rtd-theme ; extra == 'develop'
Requires-Dist: myst-parser ; extra == 'develop'
Requires-Dist: sphinx-copybutton ; extra == 'develop'
Requires-Dist: black ; extra == 'develop'
Requires-Dist: jinja2 ; extra == 'develop'
Requires-Dist: botocore ; (python_version >= "3.6") and extra == 'develop'
Provides-Extra: docs
Requires-Dist: sphinx ; extra == 'docs'
Requires-Dist: sphinx-rtd-theme ; extra == 'docs'
Requires-Dist: myst-parser ; extra == 'docs'
Requires-Dist: sphinx-copybutton ; extra == 'docs'
Provides-Extra: kerberos
Requires-Dist: requests-kerberos ; extra == 'kerberos'
